shengyighu_mcp/__init__.py
shengyighu_mcp-0.1.0.dist-info/WHEEL
shengyighu_mcp-0.1.0.dist-info/entry_points.txt
shengyighu_mcp-0.1.0.dist-info/METADATA
shengyighu_mcp-0.1.0.dist-info/RECORD
