Metadata-Version: 2.3
Name: shengyighu-mcp
Version: 0.1.0
Summary: Add your description here
Author: guoyu
Author-email: guoyu <guoyu@sanhu.cn>
Requires-Dist: mcp[cli]>=1.12.4
Requires-Python: >=3.13
